douw/__init__.py
douw/douw.py
douw/site.py
douw/version.py
douw-0.4.1.data/scripts/douw
douw-0.4.1.dist-info/LICENSE
douw-0.4.1.dist-info/METADATA
douw-0.4.1.dist-info/WHEEL
douw-0.4.1.dist-info/top_level.txt
douw-0.4.1.dist-info/RECORD
