Metadata-Version: 2.1
Name: douw
Version: 0.4.1
Summary: Drop-in website deployment
Home-page: https://git.wukl.net/wukl/douw
Author: Luc Everse
Author-email: luc@wukl.net
License: MIT
Platform: UNKNOWN
Classifier: Programming Language :: Python
Classifier: Programming Language :: Python :: 3.8
Classifier: Environment :: Console
Classifier: Intended Audience :: System Administrators
Classifier: License :: OSI Approved :: MIT License
Classifier: Natural Language :: English
Classifier: Operating System :: POSIX
Classifier: Topic :: Internet :: WWW/HTTP :: Site Management
Requires-Python: >=3.8
